[
  {
    "type": "breakfast",
    "schedule": "7am",
    "comments": ""
  },
  {
    "id": "act-20260601-1",
    "placeId": "colina-gellert",
    "schedule": "8am a 9am",
    "comments": "Subida a la Ciudadela y Estatua de la Libertad. Empezar el día aquí antes de la colina del Castillo."
  },
  {
    "id": "act-20260601-2",
    "placeId": "castillo-buda",
    "schedule": "9am a 10:30am",
    "comments": "Ir temprano para evitar multitudes. Entrada al palacio."
  },
  {
    "id": "act-20260601-3",
    "placeId": "iglesia-matias",
    "schedule": "11:00am a 11:45am",
    "comments": "Misma colina del Castillo; a pie desde el palacio."
  },
  {
    "id": "act-20260601-4",
    "placeId": "bastion-pescadores",
    "schedule": "11:45am a 1:00pm",
    "comments": "Terraza neogótica con vistas al Danubio y Pest."
  },
  {
    "type": "lunch",
    "schedule": "1:00pm a 2:00pm",
    "comments": "Almuerzo en zona Pest antes de la basílica y el eje del Danubio."
  },
  {
    "id": "act-20260601-5",
    "placeId": "basilica-san-esteban",
    "schedule": "2:30pm a 3:30pm",
    "comments": "Basílica en Pest; subir a la cúpula si hay tiempo."
  },
  {
    "id": "act-20260601-6",
    "placeId": "palacio-de-la-bolsa",
    "schedule": "3:45pm a 4:00pm",
    "comments": "Exterior del palacio; caminata hacia el Danubio."
  },
  {
    "id": "act-20260601-8",
    "placeId": "opera-nacional-hungria",
    "schedule": "4:15pm a 5:30pm",
    "comments": "Llegar 15 min antes (4:15pm). Entrada comprada 4:30pm — visita guiada 1 h."
  },
  {
    "id": "act-20260601-9",
    "placeId": "new-york-cafe",
    "schedule": "5:40pm a 6:30pm",
    "comments": "Reservar mesa. Café histórico (~40€/persona). Cerca de la Ópera y el eje Andrássy."
  },
  {
    "id": "act-20260601-7",
    "placeId": "puente-cadenas",
    "schedule": "7:30pm a 8pm",
    "comments": "Cruce peatonal y vistas del Danubio antes de la Ópera."
  },
  {
    "id": "act-20260601-10",
    "placeId": "crucero-nocturno-danubio",
    "schedule": "8pm a 9pm",
    "comments": "Vistas iluminadas del Parlamento, Castillo de Buda, Bastión y puentes. Embarque en el Danubio."
  }
]
